gridvoting/__init__.py
gridvoting/test_gridvoting_condorcet_cycle.py
gridvoting/test_gridvoting_cupy.py
gridvoting/test_gridvoting_doublecycle.py
gridvoting/test_gridvoting_grid.py
gridvoting/test_gridvoting_replication.py
gridvoting/test_gridvoting_topcycle.py
gridvoting-0.70.0.dist-info/LICENSE.md
gridvoting-0.70.0.dist-info/METADATA
gridvoting-0.70.0.dist-info/WHEEL
gridvoting-0.70.0.dist-info/top_level.txt
gridvoting-0.70.0.dist-info/RECORD
