Metadata-Version: 2.1
Name: gridvoting
Version: 0.70.0
Summary: Spatial Voting simulations on a grid with random challengers
Home-page: https://github.com/drpaulbrewer/gridvoting
Author: Paul Brewer
Author-email: drpaulbrewer@eaftc.com
Project-URL: Bug Tracker, https://github.com/drpaulbrewer/gridvoting/issues
Classifier: Programming Language :: Python :: 3
Classifier: License :: OSI Approved :: MIT License
Classifier: Operating System :: POSIX :: Linux
Classifier: Development Status :: 3 - Alpha
Classifier: Environment :: GPU :: NVIDIA CUDA
Classifier: Intended Audience :: Science/Research
Classifier: Topic :: Scientific/Engineering :: Artificial Intelligence
Requires-Python: >=3.6
License-File: LICENSE.md
